{
  "base_price": 1950,
  "beamstation_catalog_url": "https://beamstation.com/datasets",
  "beamstation_origin": "https://beamstation.com",
  "category_group_name": "Restaurants",
  "config_category": "census",
  "config_description": "Full restaurant census covering Pleasanton, California. Filtered by the Restaurants category group, providing business profiles, review counts, contact information, and competitive benchmarks. Refreshed weekly.",
  "config_name": "All Restaurants in Pleasanton, California, US",
  "export_job_id": "b02db633-9a3c-4f85-81f6-887d184cf991",
  "github_org": "Beamstation-Datasets",
  "id_short": 965358,
  "location_name": "Pleasanton",
  "location_type": "city",
  "repo_name": "all-restaurants-in-pleasanton-california-us-sample-965358",
  "sample_b2_path": "b2-export:BeamStation-ExportFiles/965358/beamstation_965358_restaurants-us-ca_SAMPLE_DIST.csv",
  "sample_pct": 9.78,
  "sample_records": 18,
  "sample_sha256": "f655cd8e2dbf74ea8948f5b26542ee361a6ee23a43a5348b1f18fba1fe131349",
  "sample_size_bytes": 81490,
  "total_records": 184,
  "updated_at": "2026-04-21T10:03:10.903476+00:00"
}